pysailfish/__init__.py
pysailfish/app/__init__.py
pysailfish/app/EAs/MA_EA.py
pysailfish/app/EAs/MT4_Server_EA.py
pysailfish/app/EAs/MT4ClientEA.py
pysailfish/app/main.py
pysailfish/app/Mainpage.dox
pysailfish/app/test_tcp_client.py
pysailfish/app/test_tcp_server_client.py
pysailfish/internal/__init__.py
pysailfish/internal/DataCtrl/__init__.py
pysailfish/internal/DataCtrl/MT4DataCtrl/__init__.py
pysailfish/internal/DataCtrl/MT4DataCtrl/MT4DataCtrl.py
pysailfish/internal/DataCtrl/MT4DataCtrl/MT4DataCtrl_Server.py
pysailfish/internal/devTools/AtomicData.py
pysailfish/internal/devTools/ThreadClass.py
pysailfish/internal/MT_EA/account_information.py
pysailfish/internal/MT_EA/chart_operations.py
pysailfish/internal/MT_EA/common_functions.py
pysailfish/internal/MT_EA/market_info.py
pysailfish/internal/MT_EA/mt4_const.py
pysailfish/internal/MT_EA/MT4_EA.py
pysailfish/internal/MT_EA/mt4_fun_num_map.py
pysailfish/internal/MT_EA/object_functions.py
pysailfish/internal/MT_EA/predefined_variables.py
pysailfish/internal/MT_EA/technical_indicators.py
pysailfish/internal/MT_EA/timeseries_and_indicators_access.py
pysailfish/internal/MT_EA/trade_functions.py
pysailfish/internal/Network/TCPCast.py
pysailfish/internal/observability/__init__.py
pysailfish/internal/observability/log_helper.py
pysailfish/internal/observability/logging_json/__init__.py
pysailfish/internal/observability/logging_json/_formatter.py
pysailfish/internal/observability/logging_json/version.py
pysailfish/internal/observability/logstash/__init__.py
pysailfish/internal/observability/logstash/formatter.py
pysailfish/internal/observability/logstash/handler_amqp.py
pysailfish/internal/observability/logstash/handler_tcp.py
pysailfish/internal/observability/logstash/handler_udp.py
pysailfish-1.18.0.dist-info/METADATA
pysailfish-1.18.0.dist-info/WHEEL
pysailfish-1.18.0.dist-info/RECORD
