Metadata-Version: 2.1
Name: pysailfish
Version: 1.18.0
Summary: 
Author: SulfredLee
Author-email: sflee1112@gmail.com
Requires-Python: >=3.8,<4.0
Classifier: Programming Language :: Python :: 3
Classifier: Programming Language :: Python :: 3.8
Classifier: Programming Language :: Python :: 3.9
Classifier: Programming Language :: Python :: 3.10
Classifier: Programming Language :: Python :: 3.11
